<?xml version="1.0" encoding="utf-8"?>
<odoo>
    <template id="report_balance_sheet_pdf" inherit_id="accounting_pdf_reports.report_financial" name="Custom Balance Sheet PDF">
        <xpath expr="//t[@t-call='accounting_pdf_reports.report_financial_body']" position="replace">
            <t t-call="accounting_pdf_reports.report_financial_body">
                <!-- You can add your custom title or footer here -->
                <div class="text-center mb-3">
                    <h2><strong>Custom Balance Sheet Report</strong></h2>
                </div>
            </t>
        </xpath>
    </template>

    <!-- Register the report action -->
    <report
        id="action_report_balance_sheet_pdf"
        model="accounting.report"
        string="Balance Sheet PDF"
        report_type="qweb-pdf"
        name="custom_bs_pl_module.report_balance_sheet_pdf"
        file="custom_bs_pl_module.report_balance_sheet_pdf"
        print_report_name="'Balance Sheet - %s' % (object.date_to or '')"
    />
</odoo>
